invertedai/__init__.py
invertedai/api/__init__.py
invertedai/api/blame.py
invertedai/api/config.py
invertedai/api/drive.py
invertedai/api/initialize.py
invertedai/api/light.py
invertedai/api/location.py
invertedai/api/mock.py
invertedai/common.py
invertedai/cosimulation.py
invertedai/error.py
invertedai/future.py
invertedai/large/__init__.py
invertedai/large/_quadtree.py
invertedai/large/common.py
invertedai/large/drive.py
invertedai/large/initialize.py
invertedai/logs/debug_logger.py
invertedai/logs/diagnostics.py
invertedai/logs/logger.py
invertedai/logs/run_scenario_suite.py
invertedai/logs/scenario_test_suite/IAI_test_suite_0a_merge_conflict.json
invertedai/logs/scenario_test_suite/IAI_test_suite_0b_merging.json
invertedai/logs/scenario_test_suite/IAI_test_suite_0c_highway_travel.json
invertedai/logs/scenario_test_suite/IAI_test_suite_1a_oneway.json
invertedai/logs/scenario_test_suite/IAI_test_suite_2a_no_forced_lane_change.json
invertedai/logs/scenario_test_suite/IAI_test_suite_3a_busy_roundabout.json
invertedai/logs/scenario_test_suite/IAI_test_suite_4a_intersection_yellow.json
invertedai/logs/scenario_test_suite/IAI_test_suite_5a_unnprotected_left_turn.json
invertedai/logs/scenario_test_suite/IAI_test_suite_5b_side_road_green.json
invertedai/utils.py
invertedai-0.0.21.dist-info/LICENSE
invertedai-0.0.21.dist-info/METADATA
invertedai-0.0.21.dist-info/WHEEL
invertedai-0.0.21.dist-info/RECORD
