Metadata-Version: 2.1
Name: invertedai
Version: 0.0.21
Summary: Client SDK for InvertedAI
License: MIT
Author: Inverted AI
Author-email: info@inverted.ai
Requires-Python: >=3.10,<3.13
Classifier: License :: OSI Approved :: MIT License
Classifier: Programming Language :: Python :: 3
Classifier: Programming Language :: Python :: 3.10
Classifier: Programming Language :: Python :: 3.11
Classifier: Programming Language :: Python :: 3.12
Requires-Dist: matplotlib (>=3.6.2,<4.0.0)
Requires-Dist: numpy (>=1.24.4,<2.0.0)
Requires-Dist: pydantic (>=2.5.3,<3.0.0)
Requires-Dist: requests (>=2.28.1,<3.0.0)
Requires-Dist: tqdm (>=4.65.0,<5.0.0)
